cg_pytest_reporter/__init__.py
cg_pytest_reporter/plugin.py
cg_pytest_reporter-2024.2.26.1340.dist-info/METADATA
cg_pytest_reporter-2024.2.26.1340.dist-info/WHEEL
cg_pytest_reporter-2024.2.26.1340.dist-info/entry_points.txt
cg_pytest_reporter-2024.2.26.1340.dist-info/RECORD
